pollination/incident_irradiance/__init__.py
pollination/incident_irradiance/_raytracing.py
pollination/incident_irradiance/entry.py
pollination_incident_irradiance-0.2.0.dist-info/LICENSE
pollination_incident_irradiance-0.2.0.dist-info/METADATA
pollination_incident_irradiance-0.2.0.dist-info/WHEEL
pollination_incident_irradiance-0.2.0.dist-info/top_level.txt
pollination_incident_irradiance-0.2.0.dist-info/RECORD
