Metadata-Version: 2.1
Name: pollination-incident-irradiance
Version: 0.2.0
Summary: Incident irradiance recipe for Pollination.
Home-page: https://github.com/pollination/incident-irradiance
Author: ladybug-tools
Author-email: info@ladybug.tools
Maintainer: mostapha, ladybug-tools
Maintainer-email: mostapha@ladybug.tools, info@ladybug.tools
License: PolyForm Shield License 1.0.0, https://polyformproject.org/wp-content/uploads/2020/06/PolyForm-Shield-1.0.0.txt
Project-URL: icon, https://raw.githubusercontent.com/ladybug-tools/artwork/master/icons_components/ladybug/png/incidentrad.png
Project-URL: docker, https://hub.docker.com/r/ladybugtools/honeybee-radiance
Keywords: honeybee,radiance,ladybug-tools,daylight,incident-irradiance
Platform: UNKNOWN
Requires-Dist: pollination-honeybee-radiance (>=0.11.8)
Requires-Dist: pollination-alias (>=0.8.1)
Requires-Dist: pollination-path (>=0.2.0)
